nf_robot/__init__.py
nf_robot/common/__init__.py
nf_robot/common/config_loader.py
nf_robot/common/cv_common.py
nf_robot/common/definitions.py
nf_robot/common/kalman_filter.py
nf_robot/common/pose_functions.py
nf_robot/common/util.py
nf_robot/generated/__init__.py
nf_robot/generated/message_pool.py
nf_robot/generated/py.typed
nf_robot/generated/google/__init__.py
nf_robot/generated/google/protobuf/__init__.py
nf_robot/generated/nf/__init__.py
nf_robot/generated/nf/common/__init__.py
nf_robot/generated/nf/config/__init__.py
nf_robot/generated/nf/control/__init__.py
nf_robot/generated/nf/telemetry/__init__.py
nf_robot/host/__init__.py
nf_robot/host/anchor_client.py
nf_robot/host/arp_gripper_client.py
nf_robot/host/calibration.py
nf_robot/host/data_store.py
nf_robot/host/frequency_estimator.py
nf_robot/host/gripper_client.py
nf_robot/host/observer.py
nf_robot/host/position_estimator.py
nf_robot/host/stats.py
nf_robot/host/target_queue.py
nf_robot/host/video_streamer.py
nf_robot/ml/__init__.py
nf_robot/ml/centering.py
nf_robot/ml/control_service.py
nf_robot/ml/target_heatmap.py
nf_robot/protos/common.proto
nf_robot/protos/control.proto
nf_robot/protos/robot-config.proto
nf_robot/protos/telemetry.proto
nf_robot/qa/__init__.py
nf_robot/qa/anchor_eval.py
nf_robot/qa/gripper_arp_eval.py
nf_robot/qa/gripper_eval.py
nf_robot/robot/__init__.py
nf_robot/robot/anchor_server.py
nf_robot/robot/component_server.py
nf_robot/robot/connect_wifi.py
nf_robot/robot/debug_motor.py
nf_robot/robot/gripper_arp_server.py
nf_robot/robot/gripper_server.py
nf_robot/robot/mks42c_motor.py
nf_robot/robot/simple_st3215.py
nf_robot/robot/spools.py
nf_robot/scripts/add_wifi_config.sh
nf_robot/scripts/install_pi.sh
nf_robot/scripts/local_deploy.py
nf_robot-1.2.1.dist-info/licenses/LICENSE
nf_robot-1.2.1.dist-info/METADATA
nf_robot-1.2.1.dist-info/WHEEL
nf_robot-1.2.1.dist-info/entry_points.txt
nf_robot-1.2.1.dist-info/top_level.txt
nf_robot-1.2.1.dist-info/RECORD
