Metadata-Version: 2.4
Name: nf_robot
Version: 1.2.1
Summary: Robot control system for Stringman
Author-email: Nathaniel Nifong <naavox@gmail.com>
License: Apache 2.0
Requires-Python: >=3.11
License-File: LICENSE
Requires-Dist: numpy>=2.0
Requires-Dist: zeroconf
Requires-Dist: asyncio
Requires-Dist: websockets
Requires-Dist: betterproto2
Requires-Dist: opencv-contrib-python-headless>=4.0
Provides-Extra: host
Requires-Dist: scipy; extra == "host"
Requires-Dist: torch>=2.4.0; extra == "host"
Requires-Dist: torchvision; extra == "host"
Requires-Dist: pupil-apriltags; extra == "host"
Requires-Dist: av; extra == "host"
Requires-Dist: huggingface_hub; extra == "host"
Provides-Extra: dev
Requires-Dist: pytest; extra == "dev"
Requires-Dist: pytest-cov; extra == "dev"
Requires-Dist: grpcio-tools; extra == "dev"
Requires-Dist: betterproto2_compiler; extra == "dev"
Requires-Dist: opencv-contrib-python>=4.0; extra == "dev"
Provides-Extra: pi
Requires-Dist: pyserial; extra == "pi"
Requires-Dist: getmac; extra == "pi"
Requires-Dist: inventorhatmini; extra == "pi"
Requires-Dist: gpiodevice; extra == "pi"
Requires-Dist: Adafruit-Blinka; extra == "pi"
Requires-Dist: adafruit-circuitpython-bno08x; extra == "pi"
Requires-Dist: adafruit-circuitpython-vl53l1x; extra == "pi"
Requires-Dist: adafruit-circuitpython-ads1x15; extra == "pi"
Requires-Dist: RPi.GPIO; extra == "pi"
Requires-Dist: pyzbar; extra == "pi"
Dynamic: license-file
